<?xml version="1.0" encoding="UTF-8"?>
<objects serializationModel="Studio.02.03.00">
	<object class="EncodingSetting" id="{01bdc3e8-fba8-4251-8ba5-6b31c3c90c46}">
		<property name="encodingFormat">
			<value>3</value>
		</property>
		<property name="quality">
			<value>37</value>
		</property>
		<relationship name="platform">
			<destination>{afb17ece-9be4-4ea2-be05-de32919c72ee}</destination>
		</relationship>
		<relationship name="encodable">
			<destination>{afb17ece-9be4-4ea2-be05-de32919c72ee}</destination>
		</relationship>
	</object>
</objects>
